slush_list/__init__.py
slush_list/main.py
slush_list/slush_list.py
slush_list/test_slush.py
slush_list-0.5.1.dist-info/LICENSE
slush_list-0.5.1.dist-info/METADATA
slush_list-0.5.1.dist-info/WHEEL
slush_list-0.5.1.dist-info/top_level.txt
slush_list-0.5.1.dist-info/RECORD
