Metadata-Version: 2.1
Name: slush-list
Version: 0.5.1
Summary: Микросервис для работы со списками слушателей и интеграцией с gitlab
Home-page: https://gitlab.com/anetto-/slush-lists
Author: Nazar_lex
Author-email: sasha.nazarov00@gmail.com
License: UNKNOWN
Platform: UNKNOWN
Classifier: Programming Language :: Python :: 3
Classifier: License :: OSI Approved :: MIT License
Classifier: Operating System :: OS Independent
Requires-Python: >=3.6
License-File: LICENSE
